anonapi/__init__.py
anonapi/batch.py
anonapi/cli/__init__.py
anonapi/cli/batch_commands.py
anonapi/cli/click_parameter_types.py
anonapi/cli/create_commands.py
anonapi/cli/entrypoint.py
anonapi/cli/job_commands.py
anonapi/cli/map_commands.py
anonapi/cli/select_commands.py
anonapi/cli/server_commands.py
anonapi/cli/settings_commands.py
anonapi/cli/user_commands.py
anonapi/client.py
anonapi/context.py
anonapi/decorators.py
anonapi/exceptions.py
anonapi/inputfile.py
anonapi/logging.py
anonapi/mapper.py
anonapi/objects.py
anonapi/parameters.py
anonapi/paths.py
anonapi/persistence.py
anonapi/responses.py
anonapi/selection.py
anonapi/settings.py
anonapi/testresources.py
anonapi-2.1.1.dist-info/LICENSE
anonapi-2.1.1.dist-info/METADATA
anonapi-2.1.1.dist-info/WHEEL
anonapi-2.1.1.dist-info/entry_points.txt
anonapi-2.1.1.dist-info/RECORD
