Metadata-Version: 2.1
Name: anonapi
Version: 2.1.1
Summary: Client and tools for working with the anoymization web API
License: MIT
Author: sjoerdk
Author-email: sjoerd.kerkstra@radboudumc.nl
Requires-Python: >=3.8,<4.0
Classifier: License :: OSI Approved :: MIT License
Classifier: Programming Language :: Python :: 3
Classifier: Programming Language :: Python :: 3.8
Classifier: Programming Language :: Python :: 3.9
Classifier: Programming Language :: Python :: 3.10
Classifier: Programming Language :: Python :: 3.11
Classifier: Programming Language :: Python :: 3.12
Classifier: Programming Language :: Python :: 3.13
Requires-Dist: click (>=8.1.3,<9.0.0)
Requires-Dist: factory-boy (>=3.2.1,<4.0.0)
Requires-Dist: fileselection (>=0.3.2,<0.4.0)
Requires-Dist: openpyxl (>=3.1.0,<4.0.0)
Requires-Dist: pydicom (>=2.3.1,<3.0.0)
Requires-Dist: requests (>=2.32.3,<3.0.0)
Requires-Dist: tabulate (>=0.9.0,<0.10.0)
Requires-Dist: tqdm (>=4.64.1,<5.0.0)
